{
  "DataContractVersion": "1.1",
  "DocumentTypes": [
    {
      "DocumentTypeId": "Accounting.NoCategory.Invoice",
      "Group": "Accounting",
      "Category": "Incoming",
      "Name": "Invoice",
      "OptionalUniqueIdentifier": "",
      "TypeField": {
        "FieldId": "Accounting.NoCategory.Invoice.DocumentType",
        "FieldName": "Document Type"
      },
      "Fields": [
        {
          "FieldId": "Accounting.NoCategory.Invoice.company-name",
          "FieldName": "company-name",
          "IsMultiValue": false,
          "Type": "Text",
          "DeriveFieldsFormat": "",
          "Components": [],
          "SetValues": [],
          "Metadata": [
            {
              "Key": "Color",
              "Value": "#038a18"
            },
            {
              "Key": "Hotkey",
              "Value": "c"
            }
          ]
        },
        {
          "FieldId": "Accounting.NoCategory.Invoice.address",
          "FieldName": "address",
          "IsMultiValue": false,
          "Type": "Address",
          "DeriveFieldsFormat": "",
          "Components": [],
          "SetValues": [],
          "Metadata": [
            {
              "Key": "Color",
              "Value": "#fa6616"
            },
            {
              "Key": "Hotkey",
              "Value": "a"
            }
          ]
        },
        {
          "FieldId": "Accounting.NoCategory.Invoice.invoice-no",
          "FieldName": "invoice-no",
          "IsMultiValue": false,
          "Type": "Number",
          "DeriveFieldsFormat": "",
          "Components": [],
          "SetValues": [],
          "Metadata": [
            {
              "Key": "Color",
              "Value": "#8a97a0"
            },
            {
              "Key": "Hotkey",
              "Value": "v"
            }
          ]
        },
        {
          "FieldId": "Accounting.NoCategory.Invoice.invoice-date",
          "FieldName": "invoice-date",
          "IsMultiValue": false,
          "Type": "Date",
          "DeriveFieldsFormat": "",
          "Components": [],
          "SetValues": [],
          "Metadata": [
            {
              "Key": "Color",
              "Value": "#6eb84a"
            },
            {
              "Key": "Hotkey",
              "Value": "e"
            }
          ]
        },
        {
          "FieldId": "Accounting.NoCategory.Invoice.total",
          "FieldName": "total",
          "IsMultiValue": false,
          "Type": "Number",
          "DeriveFieldsFormat": "",
          "Components": [],
          "SetValues": [],
          "Metadata": [
            {
              "Key": "Color",
              "Value": "#d0c04a"
            },
            {
              "Key": "Hotkey",
              "Value": "l"
            }
          ]
        },
        {
          "FieldId": "Accounting.NoCategory.Invoice.line-items",
          "FieldName": "line-items",
          "IsMultiValue": false,
          "Type": "Table",
          "DeriveFieldsFormat": "",
          "Components": [
            {
              "FieldId": "Accounting.NoCategory.Invoice.line-items.quantity",
              "FieldName": "quantity",
              "IsMultiValue": false,
              "Type": "Number",
              "DeriveFieldsFormat": "",
              "Components": [],
              "SetValues": [],
              "Metadata": []
            },
            {
              "FieldId": "Accounting.NoCategory.Invoice.line-items.description",
              "FieldName": "description",
              "IsMultiValue": false,
              "Type": "Text",
              "DeriveFieldsFormat": "",
              "Components": [],
              "SetValues": [],
              "Metadata": []
            },
            {
              "FieldId": "Accounting.NoCategory.Invoice.line-items.unit-price",
              "FieldName": "unit-price",
              "IsMultiValue": false,
              "Type": "Number",
              "DeriveFieldsFormat": "",
              "Components": [],
              "SetValues": [],
              "Metadata": []
            },
            {
              "FieldId": "Accounting.NoCategory.Invoice.line-items.item-amout",
              "FieldName": "item-amout",
              "IsMultiValue": false,
              "Type": "Number",
              "DeriveFieldsFormat": "",
              "Components": [],
              "SetValues": [],
              "Metadata": []
            }
          ],
          "SetValues": [],
          "Metadata": [
            {
              "Key": "Color",
              "Value": "#ea22cf"
            },
            {
              "Key": "Hotkey",
              "Value": "m"
            }
          ]
        },
        {
          "FieldId": "Accounting.NoCategory.Invoice.sub-total",
          "FieldName": "sub-total",
          "IsMultiValue": false,
          "Type": "Number",
          "DeriveFieldsFormat": "",
          "Components": [],
          "SetValues": [],
          "Metadata": [
            {
              "Key": "Color",
              "Value": "#c092a7"
            },
            {
              "Key": "Hotkey",
              "Value": "q"
            }
          ]
        },
        {
          "FieldId": "Accounting.NoCategory.Invoice.vat",
          "FieldName": "vat",
          "IsMultiValue": false,
          "Type": "Text",
          "DeriveFieldsFormat": "",
          "Components": [],
          "SetValues": [],
          "Metadata": [
            {
              "Key": "Color",
              "Value": "#89dd38"
            },
            {
              "Key": "Hotkey",
              "Value": "w"
            }
          ]
        }
      ]
    }
  ],
  "Groups": [
    {
      "Name": "Accounting",
      "Categories": [
        "Incoming"
      ]
    }
  ],
  "SupportedLanguages": [
    {
      "Name": "Undetermined Language",
      "Code": "und"
    },
    {
      "Name": "Bulgarian",
      "Code": "bul"
    },
    {
      "Name": "Cantonese",
      "Code": "yue"
    },
    {
      "Name": "Danish",
      "Code": "dan"
    },
    {
      "Name": "Dutch",
      "Code": "nld"
    },
    {
      "Name": "English",
      "Code": "eng"
    },
    {
      "Name": "French",
      "Code": "fra"
    },
    {
      "Name": "Georgian",
      "Code": "kat"
    },
    {
      "Name": "German",
      "Code": "deu"
    },
    {
      "Name": "Greek",
      "Code": "ell"
    },
    {
      "Name": "Hebrew",
      "Code": "heb"
    },
    {
      "Name": "Hindi",
      "Code": "hin"
    },
    {
      "Name": "Italian",
      "Code": "ita"
    },
    {
      "Name": "Japanese",
      "Code": "jpn"
    },
    {
      "Name": "Korean",
      "Code": "kor"
    },
    {
      "Name": "Macedonian",
      "Code": "mkd"
    },
    {
      "Name": "Mandarin",
      "Code": "zho"
    },
    {
      "Name": "Marathi",
      "Code": "mar"
    },
    {
      "Name": "Norwegian",
      "Code": "nor"
    },
    {
      "Name": "Polish",
      "Code": "pol"
    },
    {
      "Name": "Portuguese",
      "Code": "por"
    },
    {
      "Name": "Romanian",
      "Code": "ron"
    },
    {
      "Name": "Russian",
      "Code": "rus"
    },
    {
      "Name": "Serbian",
      "Code": "srp"
    },
    {
      "Name": "Spanish",
      "Code": "spa"
    },
    {
      "Name": "Swedish",
      "Code": "swe"
    },
    {
      "Name": "Telugu",
      "Code": "tel"
    }
  ]
}